watchmen_inquiry_trino/__init__.py
watchmen_inquiry_trino/exception.py
watchmen_inquiry_trino/settings.py
watchmen_inquiry_trino/trino_storage.py
watchmen_inquiry_trino/trino_storage_helper.py
watchmen_inquiry_trino/trino_storage_spi.py
watchmen_inquiry_trino-18.0.1.dist-info/METADATA
watchmen_inquiry_trino-18.0.1.dist-info/WHEEL
watchmen_inquiry_trino-18.0.1.dist-info/licenses/LICENSE
watchmen_inquiry_trino-18.0.1.dist-info/RECORD
